Metadata-Version: 1.1
Name: sample-pckg-publish
Version: 0.1
Summary: A new package
Home-page: https://github.com/harshith1999/sample_pckg_publish
Author: harshith
Author-email: harshith@gmail.com
License: MIT
Keywords: sample_pckg_publish
Platform: UNKNOWN
Classifier: Programming Language :: Python :: 3
Classifier: License :: OSI Approved :: MIT License
Classifier: Operating System :: OS Independent
